yarrow/__init__.py
yarrow/_version.py
yarrow/_yarrow_version.py
yarrow/main.py
yarrow/utils.py
yarrow/yarrow.py
yarrow/yarrow_cls.py
yarrow/cli/__init__.py
yarrow/cli/check.py
yarrow/cli/open.py
yarrow/cli/save.py
yarrowformat-2.1.2.dist-info/LICENSE
yarrowformat-2.1.2.dist-info/METADATA
yarrowformat-2.1.2.dist-info/WHEEL
yarrowformat-2.1.2.dist-info/entry_points.txt
yarrowformat-2.1.2.dist-info/top_level.txt
yarrowformat-2.1.2.dist-info/RECORD
