Metadata-Version: 2.1
Name: yarrowformat
Version: 2.1.2
Summary: Yarrow Format parsing lib
Home-page: https://github.com/michelin/YarrowFormat
Author: Mathieu Pichon
Author-email: mathieu.pichon_ext@michelin.com
License: UNKNOWN
Platform: UNKNOWN
Requires-Python: >=3.8
License-File: LICENSE
Requires-Dist: setuptools
Requires-Dist: wheel
Requires-Dist: pydantic (>=2.0)
Requires-Dist: numpy (>=1.19)
Requires-Dist: click
Provides-Extra: dev
Requires-Dist: black (==22.8.0) ; extra == 'dev'
Requires-Dist: isort ; extra == 'dev'
Requires-Dist: autoflake ; extra == 'dev'
Requires-Dist: pytest ; extra == 'dev'
Requires-Dist: pytest-cov ; extra == 'dev'
Requires-Dist: sphinx ; extra == 'dev'
Requires-Dist: sphinx-rtd-theme ; extra == 'dev'
